README.txt
setup.py
gpio3/__init__.py
gpio3/gpio.py
gpio3/util.py
gpio3.egg-info/PKG-INFO
gpio3.egg-info/SOURCES.txt
gpio3.egg-info/dependency_links.txt
gpio3.egg-info/top_level.txt