Metadata-Version: 1.1
Name: gpio3
Version: 3.0.1
Summary: GPIO access module
Home-page: https://hydra.ecd.space/f/gpio3/
Author: Eduard Christian Dumitrescu
Author-email: eduard.c.dumitrescu@gmail.com
License: LGPLv3
Platform: UNKNOWN
Classifier: Programming Language :: Python :: 3 :: Only
